carlapy/__init__.py
carlapy/__main__.py
carlapy/carla_game.py
carlapy/carla_utils.py
carlapy/carlapy.py
carlapy/utils.py
carlapy-0.1.3.dist-info/METADATA
carlapy-0.1.3.dist-info/WHEEL
carlapy-0.1.3.dist-info/entry_points.txt
carlapy-0.1.3.dist-info/RECORD
