Metadata-Version: 2.3
Name: carlapy
Version: 0.1.3
Summary: Add your description here
Author-email: todo <todo@todo.todo>
Requires-Python: ~=3.10
Requires-Dist: autonomous-proto>=0.1.4
Requires-Dist: carla>=0.9.15
Requires-Dist: numpy>=2.2.6
Requires-Dist: pygame>=2.6.1
Requires-Dist: rosbags>=0.10.10
Requires-Dist: typer>=0.15.4
